dolphins_recognition_challenge/__init__.py
dolphins_recognition_challenge/_nbdev.py
dolphins_recognition_challenge/convert_raw_jpg.py
dolphins_recognition_challenge/datasets.py
dolphins_recognition_challenge/helpers.py
dolphins_recognition_challenge/image_resize.py
dolphins_recognition_challenge/leaderboard.py
dolphins_recognition_challenge/submissions.py
dolphins_recognition_challenge/utils.py
dolphins_recognition_challenge/instance_segmentation/__init__.py
dolphins_recognition_challenge/instance_segmentation/model.py
dolphins_recognition_challenge-0.0.19.dist-info/LICENSE
dolphins_recognition_challenge-0.0.19.dist-info/METADATA
dolphins_recognition_challenge-0.0.19.dist-info/WHEEL
dolphins_recognition_challenge-0.0.19.dist-info/entry_points.txt
dolphins_recognition_challenge-0.0.19.dist-info/top_level.txt
dolphins_recognition_challenge-0.0.19.dist-info/RECORD
