Metadata-Version: 2.1
Name: dolphins-recognition-challenge
Version: 0.0.19
Summary: The first challange of Croatian AI league - dolphins recognition
Home-page: https://github.com/cro-ai-league/dolphins-recognition-challenge/tree/master/
Author: Davor Runje
Author-email: davor.runje@cisex.org
License: Apache Software License 2.0
Keywords: machine learning,deep learning,challenge,AI,CISEx,Croatian AI League,dolphins,Blue world institute
Platform: UNKNOWN
Classifier: Development Status :: 5 - Production/Stable
Classifier: Intended Audience :: Developers
Classifier: License :: OSI Approved :: Apache Software License
Classifier: Natural Language :: English
Classifier: Programming Language :: Python :: 3.6
Classifier: Programming Language :: Python :: 3.7
Classifier: Programming Language :: Python :: 3.8
Requires-Python: >=3.6
Requires-Dist: torch (==1.7.1)
Requires-Dist: numpy (>=1.18.5)
Requires-Dist: pandas (>=1.1.5)
Requires-Dist: torchvision (==0.8.2)
Requires-Dist: Pillow (>=7.2.0)
Requires-Dist: pycocotools (>=2.0.2)
Requires-Dist: GitPython (>=3.1.11)
Requires-Dist: keyrings.alt (>=4.0.1)
Requires-Dist: seaborn (>=0.11.0)
Requires-Dist: boto3 (>=1.16.41)
Requires-Dist: requests (>=2.24.0)
Requires-Dist: progressbar2 (>=2.4.0)
Requires-Dist: tabulate (>=0.8.7)
